faker_web/__init__.py
faker_web/mimetypes.py
faker_web-0.3.1.dist-info/LICENSE
faker_web-0.3.1.dist-info/METADATA
faker_web-0.3.1.dist-info/NOTICE
faker_web-0.3.1.dist-info/WHEEL
faker_web-0.3.1.dist-info/top_level.txt
faker_web-0.3.1.dist-info/zip-safe
faker_web-0.3.1.dist-info/RECORD
